{
  "id": "chakram-of-destiny",
  "name": "Chakram of Destiny",
  "base_skill": "Chakram Shields",
  "morph_of": "chakram-shields",
  "morph_sibling": "tidal-chakram",
  "morph_rationale": "Stack morph — recasting on an already-shielded target grants a 30% stronger shield and generates Crux; preferred over Tidal Chakram when layering shields and generating Crux matter more than converting shields to healing.",
  "class": "Arcanist",
  "skill_line": "Curative Runeforms",
  "skill_line_id": "curative-runeforms",
  "type": "Active",
  "resource": "Magicka",
  "icon": "/assets/skills/chakram-of-destiny.png",
  "patch_verified": "U49",
  "esohub_url": "https://eso-hub.com/en/skills/arcanist/curative-runeforms/chakram-of-destiny",
  "uesp_url": "https://en.uesp.net/wiki/Online:Chakram_of_Destiny"
}
