{
  "id": "dazing-explosion",
  "name": "Dazing Explosion",
  "base_skill": null,
  "morph_of": null,
  "morph_sibling": null,
  "class": "Weapon",
  "skill_line": "Destruction Staff",
  "skill_line_id": "destruction-staff",
  "type": "Active",
  "resource": "None",
  "icon": "/assets/skills/dazing-explosion.png",
  "patch_verified": "U49",
  "esohub_url": "https://eso-hub.com/en/skills/weapon/destruction-staff/dazing-explosion",
  "uesp_url": "https://en.uesp.net/wiki/Online:Dazing_Explosion"
}
