{
  "id": "way-of-fire",
  "name": "Way of Fire",
  "type": "Mixed",
  "acquisition": "Overland",
  "location": "Craglorn",
  "dlc": "Base Game",
  "pieces": 5,
  "slots": [
    "necklace",
    "ring",
    "weapon",
    "off-hand"
  ],
  "patch_verified": "U49",
  "bonuses": [
    {
      "count": 2,
      "stat": "Weapon and Spell Damage",
      "value": 129
    },
    {
      "count": 3,
      "stat": "Maximum Health",
      "value": 1206
    },
    {
      "count": 4,
      "stat": "Critical Chance",
      "value": 657
    },
    {
      "count": 5,
      "stat": "When you deal damage with a Light or Heavy Attack, you deal an additional 571 Flame damage. This effect can occur once every 2 seconds and scales off the higher of your Weapon or Spell Damage.",
      "value": ""
    }
  ],
  "uesp_url": "https://en.uesp.net/wiki/Online:Way_of_Fire",
  "esohub_url": "https://eso-hub.com/en/sets/way-of-fire"
}
