{
  "id": "witch-knights-defiance",
  "name": "Witch-Knight's Defiance",
  "type": "Mixed",
  "acquisition": "Overland",
  "location": "The Reach",
  "dlc": "Base Game",
  "pieces": 5,
  "slots": [
    "necklace",
    "ring",
    "weapon",
    "off-hand"
  ],
  "patch_verified": "U49",
  "bonuses": [
    {
      "count": 2,
      "stat": "Weapon and Spell Damage",
      "value": 129
    },
    {
      "count": 3,
      "stat": "Weapon and Spell Damage",
      "value": 129
    },
    {
      "count": 4,
      "stat": "Weapon and Spell Damage",
      "value": 129
    },
    {
      "count": 5,
      "stat": "Increases your Weapon and Spell Damage by 8-369 against enemies inflicted with a Poison Damage effect.",
      "value": ""
    }
  ],
  "uesp_url": "https://en.uesp.net/wiki/Online:Witch-Knight's_Defiance",
  "esohub_url": "https://eso-hub.com/en/sets/witch-knights-defiance"
}
