{
  "id": "witchman-armor",
  "name": "Witchman Armor",
  "type": "Mixed",
  "acquisition": "Overland",
  "location": "The Rift",
  "dlc": "Base Game",
  "pieces": 5,
  "slots": [
    "necklace",
    "ring",
    "weapon",
    "off-hand"
  ],
  "patch_verified": "U49",
  "bonuses": [
    {
      "count": 2,
      "stat": "Stamina Recovery",
      "value": 129
    },
    {
      "count": 3,
      "stat": "Weapon and Spell Damage",
      "value": 129
    },
    {
      "count": 4,
      "stat": "Maximum Health",
      "value": 1206
    },
    {
      "count": 5,
      "stat": "When you use an Ultimate ability, you heal for 1-51 Health and restore 1-51 Stamina and Magicka per Ultimate spent.",
      "value": ""
    }
  ],
  "uesp_url": "https://en.uesp.net/wiki/Online:Witchman_Armor",
  "esohub_url": "https://eso-hub.com/en/sets/witchman-armor"
}
