{
  "id": "giant-spider",
  "name": "Giant Spider",
  "type": "Monster",
  "acquisition": "Overland",
  "location": "No longer dropped",
  "dlc": "Base Game",
  "pieces": 2,
  "slots": [
    "head"
  ],
  "patch_verified": "U49",
  "bonuses": [
    {
      "count": 1,
      "stat": "Adds 4% Healing Taken",
      "value": ""
    },
    {
      "count": 2,
      "stat": "When you Block an enemy that is between 8 and 22 meters from you, you spin strands of spider silk to pull the enemy to you and taunt them for 15 seconds if they are not already taunted. This effect can occur once every 1 second.",
      "value": ""
    }
  ],
  "uesp_url": "https://en.uesp.net/wiki/Online:Giant_Spider",
  "esohub_url": "https://eso-hub.com/en/sets/giant-spider"
}
