{
  "id": "meritorious-service",
  "name": "Meritorious Service",
  "type": "Mixed",
  "acquisition": "PvP",
  "location": "Tel Var Merchant",
  "dlc": "Base Game",
  "pieces": 5,
  "slots": [
    "necklace",
    "ring",
    "weapon",
    "off-hand"
  ],
  "patch_verified": "U49",
  "bonuses": [
    {
      "count": 2,
      "stat": "Maximum Health",
      "value": 1206
    },
    {
      "count": 3,
      "stat": "Maximum Magicka",
      "value": 1096
    },
    {
      "count": 4,
      "stat": "Weapon and Spell Damage",
      "value": 129
    },
    {
      "count": 5,
      "stat": "When you cast a Support ability while in combat, you increase the Physical and Spell Resistance of yourself and up to 5 group members within 10 meters by 82-3540 for 20 seconds.",
      "value": ""
    }
  ],
  "uesp_url": "https://en.uesp.net/wiki/Online:Meritorious_Service",
  "esohub_url": "https://eso-hub.com/en/sets/meritorious-service"
}
